geopolitex_analyzer/__init__.py
geopolitex_analyzer/main.py
geopolitex_analyzer/prompts.py
geopolitex_analyzer-2025.12.21165107.dist-info/METADATA
geopolitex_analyzer-2025.12.21165107.dist-info/WHEEL
geopolitex_analyzer-2025.12.21165107.dist-info/top_level.txt
geopolitex_analyzer-2025.12.21165107.dist-info/RECORD
