Metadata-Version: 2.4
Name: geopolitex-analyzer
Version: 2025.12.21165107
Summary: A new package that processes news headlines or short text inputs related to geopolitical and defense topics, such as reports on military capabilities or international competition. It uses an LLM to ge
Author-email: geopolitex-analyzer <hi@eugene.plus>
License: MIT
Project-URL: Homepage, https://github.com/chigwell/geopolitex-analyzer
Requires-Python: >=3.9
Requires-Dist: langchain-llm7>=0.0.0
Requires-Dist: llmatch-messages>=0.0.0
Requires-Dist: langchain-core>=0.3.0
